langchain_prolog/__init__.py
langchain_prolog/__version__.py
langchain_prolog/_prolog_init.py
langchain_prolog/consult_ex.pl
langchain_prolog/exceptions.py
langchain_prolog/logger.py
langchain_prolog/runnable.py
langchain_prolog/tool.py
langchain_prolog-0.1.1.post16.dist-info/LICENSE
langchain_prolog-0.1.1.post16.dist-info/METADATA
langchain_prolog-0.1.1.post16.dist-info/WHEEL
langchain_prolog-0.1.1.post16.dist-info/RECORD
