Metadata-Version: 2.3
Name: langchain-prolog
Version: 0.1.1.post16
Summary: An integration package connecting Prolog and LangChain
License: MIT
Keywords: langchain,prolog,swi-prolog,llm,agent
Author: Antonio Pisani
Requires-Python: >=3.10,<4.0
Classifier: Development Status :: 3 - Alpha
Classifier: Intended Audience :: Developers
Classifier: License :: OSI Approved :: MIT License
Classifier: Programming Language :: Prolog
Classifier: Programming Language :: Python :: 3
Classifier: Programming Language :: Python :: 3.10
Classifier: Programming Language :: Python :: 3.11
Classifier: Programming Language :: Python :: 3.12
Classifier: Programming Language :: Python :: 3.13
Classifier: Topic :: Scientific/Engineering :: Artificial Intelligence
Classifier: Topic :: Software Development :: Libraries :: Python Modules
Requires-Dist: janus-swi (>=1.5.2,<2.0.0)
Requires-Dist: langchain (>=0.3.0,<0.4.0)
Requires-Dist: pydantic (>=2.0.0,<3.0.0)
Project-URL: Documentation, https://langchain-prolog.readthedocs.io/
Project-URL: Issue Tracker, https://github.com/apisani1/langchain-prolog/issues
Project-URL: Repository, https://github.com/apisani1/langchain-prolog
Project-URL: Release Notes, https://github.com/apisani1/langchain-prolog/releases
Project-URL: Source Code, https://github.com/apisani1/langchain-prolog
